{
    "tests.test_crypto.TestCRL.test_add_revoked_keyword": [
        "src.OpenSSL.crypto.CRL.add_revoked",
        "src.OpenSSL.crypto.CRL.get_revoked"
    ],
    "tests.test_crypto.TestCRL.test_construction": [
        "src.OpenSSL.crypto.CRL.get_revoked",
        "src.OpenSSL.crypto.CRL.__init__"
    ],
    "tests.test_crypto.TestCRL.test_convert_from_cryptography": [
        "src.OpenSSL.crypto.CRL.from_cryptography"
    ],
    "tests.test_crypto.TestCRL.test_convert_from_cryptography_unsupported_type": [
        "src.OpenSSL.crypto.CRL.from_cryptography"
    ],
    "tests.test_crypto.TestCRL.test_convert_to_cryptography_key": [
        "src.OpenSSL.crypto.CRL.to_cryptography"
    ],
    "tests.test_crypto.TestCRL.test_dump_crl": [
        "src.OpenSSL.crypto.dump_crl"
    ],
    "tests.test_crypto.TestCRL.test_export_custom_digest": [
        "src.OpenSSL.crypto.CRL.export"
    ],
    "tests.test_crypto.TestCRL.test_export_default_digest": [
        "src.OpenSSL.crypto.CRL.export"
    ],
    "tests.test_crypto.TestCRL.test_export_der": [
        "src.OpenSSL.crypto.CRL.export"
    ],
    "tests.test_crypto.TestCRL.test_export_invalid": [
        "src.OpenSSL.crypto.CRL.export"
    ],
    "tests.test_crypto.TestCRL.test_export_md5_digest": [
        "src.OpenSSL.crypto.CRL.export"
    ],
    "tests.test_crypto.TestCRL.test_export_pem": [
        "src.OpenSSL.crypto.CRL.export"
    ],
    "tests.test_crypto.TestCRL.test_export_text": [
        "src.OpenSSL.crypto.CRL.export"
    ],
    "tests.test_crypto.TestCRL.test_export_unknown_digest": [
        "src.OpenSSL.crypto.CRL.export"
    ],
    "tests.test_crypto.TestCRL.test_export_unknown_filetype": [
        "src.OpenSSL.crypto.CRL.export"
    ],
    "tests.test_crypto.TestCRL.test_export_wrong_args": [
        "src.OpenSSL.crypto.CRL.export"
    ],
    "tests.test_crypto.TestCRL.test_get_issuer": [
        "src.OpenSSL.crypto.CRL.get_issuer"
    ],
    "tests.test_crypto.TestCRL.test_get_revoked": [
        "src.OpenSSL.crypto.CRL.get_revoked"
    ],
    "tests.test_crypto.TestCRL.test_load_crl": [
        "src.OpenSSL.crypto.load_crl"
    ],
    "tests.test_crypto.TestCRL.test_load_crl_bad_data": [
        "src.OpenSSL.crypto.load_crl"
    ],
    "tests.test_crypto.TestCRL.test_load_crl_bad_filetype": [
        "src.OpenSSL.crypto.load_crl"
    ],
    "tests.test_crypto.TestCRL.test_verify_with_missing_crl": [
        "src.OpenSSL.crypto.X509StoreContext.verify_certificate",
        "src.OpenSSL.crypto.X509Store.add_crl",
        "src.OpenSSL.crypto.X509.get_subject",
        "src.OpenSSL.crypto.X509Name.__getattr__"
    ],
    "tests.test_crypto.TestCRL.test_verify_with_revoked": [
        "src.OpenSSL.crypto.X509StoreContext.verify_certificate"
    ],
    "tests.test_crypto.TestEllipticCurve.test_a_curve": [
        "src.OpenSSL.crypto.get_elliptic_curve",
        "src.OpenSSL.crypto.get_elliptic_curves"
    ],
    "tests.test_crypto.TestEllipticCurve.test_not_a_curve": [
        "src.OpenSSL.crypto.get_elliptic_curve"
    ],
    "tests.test_crypto.TestEllipticCurve.test_repr": [
        "src.OpenSSL.crypto._EllipticCurve.__repr__"
    ],
    "tests.test_crypto.TestEllipticCurve.test_set": [
        "src.OpenSSL.crypto.get_elliptic_curves"
    ],
    "tests.test_crypto.TestEllipticCurve.test_to_EC_KEY": [
        "src.OpenSSL.crypto._EllipticCurve._to_EC_KEY"
    ],
    "tests.test_crypto.TestEllipticCurveHash.test_contains": [
        "src.OpenSSL.crypto.get_elliptic_curve"
    ],
    "tests.test_crypto.TestEllipticCurveHash.test_does_not_contain": [
        "src.OpenSSL.crypto.get_elliptic_curve"
    ],
    "tests.test_crypto.TestFunction.test_dump_certificate": [
        "src.OpenSSL.crypto.dump_certificate"
    ],
    "tests.test_crypto.TestFunction.test_dump_certificate_bad_type": [
        "src.OpenSSL.crypto.dump_certificate"
    ],
    "tests.test_crypto.TestFunction.test_dump_certificate_request": [
        "src.OpenSSL.crypto.dump_certificate_request"
    ],
    "tests.test_crypto.TestFunction.test_dump_privatekey_asn1": [
        "src.OpenSSL.crypto.dump_privatekey"
    ],
    "tests.test_crypto.TestFunction.test_dump_privatekey_invalid_filetype": [
        "src.OpenSSL.crypto.dump_privatekey"
    ],
    "tests.test_crypto.TestFunction.test_dump_privatekey_invalid_passphrase_type": [
        "src.OpenSSL.crypto.dump_privatekey"
    ],
    "tests.test_crypto.TestFunction.test_dump_privatekey_invalid_pkey": [
        "src.OpenSSL.crypto.dump_privatekey"
    ],
    "tests.test_crypto.TestFunction.test_dump_privatekey_not_rsa_key": [
        "src.OpenSSL.crypto.dump_privatekey"
    ],
    "tests.test_crypto.TestFunction.test_dump_privatekey_passphrase": [
        "src.OpenSSL.crypto.dump_privatekey"
    ],
    "tests.test_crypto.TestFunction.test_dump_privatekey_passphraseCallbackLength": [
        "src.OpenSSL.crypto.dump_privatekey"
    ],
    "tests.test_crypto.TestFunction.test_dump_privatekey_passphrase_callback": [
        "src.OpenSSL.crypto.dump_privatekey"
    ],
    "tests.test_crypto.TestFunction.test_dump_privatekey_passphrase_exception": [
        "src.OpenSSL.crypto.dump_privatekey"
    ],
    "tests.test_crypto.TestFunction.test_dump_privatekey_passphrase_wrong_type": [
        "src.OpenSSL.crypto.dump_privatekey"
    ],
    "tests.test_crypto.TestFunction.test_dump_privatekey_pem": [
        "src.OpenSSL.crypto.dump_privatekey"
    ],
    "tests.test_crypto.TestFunction.test_dump_privatekey_text": [
        "src.OpenSSL.crypto.dump_privatekey"
    ],
    "tests.test_crypto.TestFunction.test_dump_privatekey_truncated": [
        "src.OpenSSL.crypto.dump_privatekey"
    ],
    "tests.test_crypto.TestFunction.test_dump_privatekey_unknown_cipher": [
        "src.OpenSSL.crypto.dump_privatekey"
    ],
    "tests.test_crypto.TestFunction.test_dump_privatekey_wrong_args": [
        "src.OpenSSL.crypto.dump_privatekey"
    ],
    "tests.test_crypto.TestFunction.test_dump_publickey_asn1": [
        "src.OpenSSL.crypto.dump_publickey"
    ],
    "tests.test_crypto.TestFunction.test_dump_publickey_invalid_type": [
        "src.OpenSSL.crypto.dump_publickey"
    ],
    "tests.test_crypto.TestFunction.test_dump_publickey_pem": [
        "src.OpenSSL.crypto.dump_publickey"
    ],
    "tests.test_crypto.TestFunction.test_load_privatekey_asn1": [
        "src.OpenSSL.crypto.load_privatekey",
        "src.OpenSSL.crypto.PKey.bits"
    ],
    "tests.test_crypto.TestFunction.test_load_privatekey_invalid_format": [
        "src.OpenSSL.crypto.load_privatekey"
    ],
    "tests.test_crypto.TestFunction.test_load_privatekey_invalid_passphrase_type": [
        "src.OpenSSL.crypto.load_privatekey"
    ],
    "tests.test_crypto.TestFunction.test_load_privatekey_passphrase": [
        "src.OpenSSL.crypto.load_privatekey"
    ],
    "tests.test_crypto.TestFunction.test_load_privatekey_passphraseCallback": [
        "src.OpenSSL.crypto.load_privatekey"
    ],
    "tests.test_crypto.TestFunction.test_load_privatekey_passphraseWrongType": [
        "src.OpenSSL.crypto.load_privatekey"
    ],
    "tests.test_crypto.TestFunction.test_load_privatekey_passphrase_callback_length": [
        "src.OpenSSL.crypto.load_privatekey"
    ],
    "tests.test_crypto.TestFunction.test_load_privatekey_passphrase_exception": [
        "src.OpenSSL.crypto.load_privatekey"
    ],
    "tests.test_crypto.TestFunction.test_load_privatekey_passphrase_wrong_return_type": [
        "src.OpenSSL.crypto.load_privatekey"
    ],
    "tests.test_crypto.TestFunction.test_load_privatekey_truncated": [
        "src.OpenSSL.crypto.load_privatekey"
    ],
    "tests.test_crypto.TestFunction.test_load_privatekey_wrongPassphrase": [
        "src.OpenSSL.crypto.load_privatekey"
    ],
    "tests.test_crypto.TestFunction.test_load_privatekey_wrongPassphraseCallback": [
        "src.OpenSSL.crypto.load_privatekey"
    ],
    "tests.test_crypto.TestLoadCertificate.test_bad_certificate": [
        "src.OpenSSL.crypto.load_certificate"
    ],
    "tests.test_crypto.TestLoadCertificate.test_bad_file_type": [
        "src.OpenSSL.crypto.load_certificate_request"
    ],
    "tests.test_crypto.TestLoadPublicKey.test_invalid_key_format": [
        "src.OpenSSL.crypto.load_publickey"
    ],
    "tests.test_crypto.TestLoadPublicKey.test_invalid_type": [
        "src.OpenSSL.crypto.load_publickey"
    ],
    "tests.test_crypto.TestLoadPublicKey.test_loading_works": [
        "src.OpenSSL.crypto.load_publickey",
        "src.OpenSSL.crypto.PKey.bits"
    ],
    "tests.test_crypto.TestLoadPublicKey.test_tolerates_unicode_strings": [
        "src.OpenSSL.crypto.dump_publickey",
        "src.OpenSSL.crypto.load_publickey"
    ],
    "tests.test_crypto.TestNetscapeSPKI.test_b64_encode": [
        "src.OpenSSL.crypto.NetscapeSPKI.b64_encode"
    ],
    "tests.test_crypto.TestNetscapeSPKI.test_construction": [
        "src.OpenSSL.crypto.NetscapeSPKI.__init__"
    ],
    "tests.test_crypto.TestNetscapeSPKI.test_invalid_attribute": [
        "src.OpenSSL.crypto.NetscapeSPKI.__init__"
    ],
    "tests.test_crypto.TestNetscapeSPKI.test_type": [
        "src.OpenSSL.crypto.NetscapeSPKI.__init__"
    ],
    "tests.test_crypto.TestPKCS12.test_cert_only": [
        "src.OpenSSL.crypto.PKCS12.get_certificate",
        "src.OpenSSL.crypto.PKCS12.get_privatekey"
    ],
    "tests.test_crypto.TestPKCS12.test_empty_construction": [
        "src.OpenSSL.crypto.PKCS12.get_certificate",
        "src.OpenSSL.crypto.PKCS12.get_ca_certificates",
        "src.OpenSSL.crypto.PKCS12.get_friendlyname",
        "src.OpenSSL.crypto.PKCS12.get_privatekey"
    ],
    "tests.test_crypto.TestPKCS12.test_export_without_args": [
        "src.OpenSSL.crypto.PKCS12.export"
    ],
    "tests.test_crypto.TestPKCS12.test_export_without_bytes": [
        "src.OpenSSL.crypto.PKCS12.export"
    ],
    "tests.test_crypto.TestPKCS12.test_export_without_mac": [
        "src.OpenSSL.crypto.PKCS12.export"
    ],
    "tests.test_crypto.TestPKCS12.test_friendly_name": [
        "src.OpenSSL.crypto.PKCS12.get_friendlyname",
        "src.OpenSSL.crypto.PKCS12.set_friendlyname"
    ],
    "tests.test_crypto.TestPKCS12.test_key_cert_mismatch": [
        "src.OpenSSL.crypto.PKCS12.export",
        "src.OpenSSL.crypto.PKCS12.set_certificate",
        "src.OpenSSL.crypto.PKCS12.set_ca_certificates"
    ],
    "tests.test_crypto.TestPKCS12.test_key_only": [
        "src.OpenSSL.crypto.PKCS12.get_privatekey",
        "src.OpenSSL.crypto.PKCS12.export",
        "src.OpenSSL.crypto.PKCS12.get_certificate"
    ],
    "tests.test_crypto.TestPKCS12.test_load_without_mac": [
        "src.OpenSSL.crypto.PKCS12.export"
    ],
    "tests.test_crypto.TestPKCS12.test_removing_ca_cert": [
        "src.OpenSSL.crypto.PKCS12.set_ca_certificates",
        "src.OpenSSL.crypto.PKCS12.get_ca_certificates"
    ],
    "tests.test_crypto.TestPKCS12.test_replace": [
        "src.OpenSSL.crypto.PKCS12.get_ca_certificates",
        "src.OpenSSL.crypto.PKCS12.set_privatekey",
        "src.OpenSSL.crypto.PKCS12.set_ca_certificates"
    ],
    "tests.test_crypto.TestPKCS12.test_type": [
        "src.OpenSSL.crypto.PKCS12.__init__"
    ],
    "tests.test_crypto.TestPKCS12.test_type_errors": [
        "src.OpenSSL.crypto.PKCS12.set_ca_certificates",
        "src.OpenSSL.crypto.PKCS12.set_privatekey",
        "src.OpenSSL.crypto.PKCS12.set_certificate"
    ],
    "tests.test_crypto.TestPKCS12.test_various_empty_passphrases": [
        "src.OpenSSL.crypto.PKCS12.export"
    ],
    "tests.test_crypto.TestPKCS12.test_zero_len_list_for_ca": [
        "src.OpenSSL.crypto.PKCS12.get_ca_certificates",
        "src.OpenSSL.crypto.PKCS12.export"
    ],
    "tests.test_crypto.TestPKey.test_check_pr_897": [
        "src.OpenSSL.crypto.PKey.check"
    ],
    "tests.test_crypto.TestPKey.test_check_public_key": [
        "src.OpenSSL.crypto.PKey.check",
        "src.OpenSSL.crypto.X509.get_pubkey",
        "src.OpenSSL.crypto.X509.set_pubkey"
    ],
    "tests.test_crypto.TestPKey.test_construction": [
        "src.OpenSSL.crypto.PKey.__init__"
    ],
    "tests.test_crypto.TestPKey.test_convert_from_cryptography_public_key": [
        "src.OpenSSL.crypto.PKey.from_cryptography_key"
    ],
    "tests.test_crypto.TestPKey.test_convert_from_cryptography_unsupported_type": [
        "src.OpenSSL.crypto.PKey.from_cryptography_key"
    ],
    "tests.test_crypto.TestPKey.test_convert_public_pkey_to_cryptography_key": [
        "src.OpenSSL.crypto.PKey.to_cryptography_key"
    ],
    "tests.test_crypto.TestPKey.test_convert_roundtrip_cryptography_private_key": [
        "src.OpenSSL.crypto.PKey.from_cryptography_key",
        "src.OpenSSL.crypto.PKey.to_cryptography_key"
    ],
    "tests.test_crypto.TestPKey.test_dsa_generation": [
        "src.OpenSSL.crypto.PKey.generate_key",
        "src.OpenSSL.crypto.PKey.type"
    ],
    "tests.test_crypto.TestPKey.test_failed_generation": [
        "src.OpenSSL.crypto.PKey.generate_key"
    ],
    "tests.test_crypto.TestPKey.test_inconsistent_key": [
        "src.OpenSSL.crypto.PKey.check",
        "src.OpenSSL.crypto.load_privatekey"
    ],
    "tests.test_crypto.TestPKey.test_pregeneration": [
        "src.OpenSSL.crypto.PKey.type"
    ],
    "tests.test_crypto.TestPKey.test_regeneration": [
        "src.OpenSSL.crypto.PKey.generate_key",
        "src.OpenSSL.crypto.PKey.bits",
        "src.OpenSSL.crypto.PKey.type"
    ],
    "tests.test_crypto.TestPKey.test_rsa_generation": [
        "src.OpenSSL.crypto.PKey.generate_key",
        "src.OpenSSL.crypto.PKey.type"
    ],
    "tests.test_crypto.TestPKey.test_type": [
        "src.OpenSSL.crypto.PKey.__init__"
    ],
    "tests.test_crypto.TestRevoked.test_construction": [
        "src.OpenSSL.crypto.Revoked.get_reason",
        "src.OpenSSL.crypto.Revoked.get_serial"
    ],
    "tests.test_crypto.TestRevoked.test_date": [
        "src.OpenSSL.crypto.Revoked.get_rev_date",
        "src.OpenSSL.crypto.Revoked.set_rev_date"
    ],
    "tests.test_crypto.TestRevoked.test_ignores_unsupported_revoked_cert_extension_get_reason": [
        "src.OpenSSL.crypto.Revoked.get_reason"
    ],
    "tests.test_crypto.TestRevoked.test_ignores_unsupported_revoked_cert_extension_set_new_reason": [
        "src.OpenSSL.crypto.Revoked.get_reason",
        "src.OpenSSL.crypto.CRL.get_revoked"
    ],
    "tests.test_crypto.TestRevoked.test_reason": [
        "src.OpenSSL.crypto.Revoked.get_reason",
        "src.OpenSSL.crypto.Revoked.set_reason"
    ],
    "tests.test_crypto.TestRevoked.test_serial": [
        "src.OpenSSL.crypto.Revoked.set_serial",
        "src.OpenSSL.crypto.Revoked.get_serial"
    ],
    "tests.test_crypto.TestRevoked.test_set_reason_invalid_reason": [
        "src.OpenSSL.crypto.Revoked.set_reason"
    ],
    "tests.test_crypto.TestRevoked.test_set_reason_wrong_args": [
        "src.OpenSSL.crypto.Revoked.set_reason"
    ],
    "tests.test_crypto.TestSignVerify.test_sign_nulls": [
        "src.OpenSSL.crypto.sign"
    ],
    "tests.test_crypto.TestSignVerify.test_sign_verify": [
        "src.OpenSSL.crypto.verify"
    ],
    "tests.test_crypto.TestSignVerify.test_sign_verify_ecdsa": [
        "src.OpenSSL.crypto.verify",
        "src.OpenSSL.crypto.sign"
    ],
    "tests.test_crypto.TestSignVerify.test_sign_verify_with_text": [
        "src.OpenSSL.crypto.verify",
        "src.OpenSSL.crypto.sign"
    ],
    "tests.test_crypto.TestSignVerify.test_sign_with_large_key": [
        "src.OpenSSL.crypto.sign"
    ],
    "tests.test_crypto.TestX509.test_construction": [
        "src.OpenSSL.crypto.X509.__init__"
    ],
    "tests.test_crypto.TestX509.test_convert_from_cryptography": [
        "src.OpenSSL.crypto.X509.from_cryptography"
    ],
    "tests.test_crypto.TestX509.test_convert_from_cryptography_unsupported_type": [
        "src.OpenSSL.crypto.X509.from_cryptography"
    ],
    "tests.test_crypto.TestX509.test_convert_to_cryptography_key": [
        "src.OpenSSL.crypto.X509.to_cryptography"
    ],
    "tests.test_crypto.TestX509.test_digest": [
        "src.OpenSSL.crypto.X509.digest"
    ],
    "tests.test_crypto.TestX509.test_extension_count": [
        "src.OpenSSL.crypto.X509.get_extension_count"
    ],
    "tests.test_crypto.TestX509.test_get_extension": [
        "src.OpenSSL.crypto.X509.get_extension"
    ],
    "tests.test_crypto.TestX509.test_get_issuer": [
        "src.OpenSSL.crypto.X509.get_issuer"
    ],
    "tests.test_crypto.TestX509.test_get_notAfter": [
        "src.OpenSSL.crypto.X509.get_notAfter"
    ],
    "tests.test_crypto.TestX509.test_get_notBefore": [
        "src.OpenSSL.crypto.X509.get_notBefore"
    ],
    "tests.test_crypto.TestX509.test_get_pubkey_uninitialized": [
        "src.OpenSSL.crypto.X509.get_pubkey"
    ],
    "tests.test_crypto.TestX509.test_get_signature_algorithm": [
        "src.OpenSSL.crypto.X509.get_signature_algorithm"
    ],
    "tests.test_crypto.TestX509.test_get_subject": [
        "src.OpenSSL.crypto.X509.get_subject"
    ],
    "tests.test_crypto.TestX509.test_get_undefined_signature_algorithm": [
        "src.OpenSSL.crypto.X509.get_signature_algorithm"
    ],
    "tests.test_crypto.TestX509.test_gmtime_adj_notAfter": [
        "src.OpenSSL.crypto.X509.gmtime_adj_notAfter"
    ],
    "tests.test_crypto.TestX509.test_gmtime_adj_notAfter_wrong_args": [
        "src.OpenSSL.crypto.X509.gmtime_adj_notAfter"
    ],
    "tests.test_crypto.TestX509.test_gmtime_adj_notBefore": [
        "src.OpenSSL.crypto.X509.gmtime_adj_notBefore"
    ],
    "tests.test_crypto.TestX509.test_gmtime_adj_notBefore_wrong_args": [
        "src.OpenSSL.crypto.X509.gmtime_adj_notBefore"
    ],
    "tests.test_crypto.TestX509.test_has_expired": [
        "src.OpenSSL.crypto.X509.has_expired"
    ],
    "tests.test_crypto.TestX509.test_has_expired_exception": [
        "src.OpenSSL.crypto.X509.has_expired"
    ],
    "tests.test_crypto.TestX509.test_has_not_expired": [
        "src.OpenSSL.crypto.X509.has_expired"
    ],
    "tests.test_crypto.TestX509.test_invalid_digest_algorithm": [
        "src.OpenSSL.crypto.X509.digest"
    ],
    "tests.test_crypto.TestX509.test_nullbyte_subjectAltName": [
        "src.OpenSSL.crypto.X509Extension.get_short_name"
    ],
    "tests.test_crypto.TestX509.test_root_has_not_expired": [
        "src.OpenSSL.crypto.X509.has_expired"
    ],
    "tests.test_crypto.TestX509.test_serial_number": [
        "src.OpenSSL.crypto.X509.get_serial_number"
    ],
    "tests.test_crypto.TestX509.test_set_issuer": [
        "src.OpenSSL.crypto.X509.set_issuer"
    ],
    "tests.test_crypto.TestX509.test_set_issuer_wrong_args": [
        "src.OpenSSL.crypto.X509.set_issuer"
    ],
    "tests.test_crypto.TestX509.test_set_notAfter": [
        "src.OpenSSL.crypto.X509.set_notAfter",
        "src.OpenSSL.crypto.X509.get_notAfter"
    ],
    "tests.test_crypto.TestX509.test_set_notBefore": [
        "src.OpenSSL.crypto.X509.set_notBefore",
        "src.OpenSSL.crypto.X509.get_notBefore"
    ],
    "tests.test_crypto.TestX509.test_set_pubkey_wrong_type": [
        "src.OpenSSL.crypto.X509.set_pubkey"
    ],
    "tests.test_crypto.TestX509.test_set_subject": [
        "src.OpenSSL.crypto.X509.set_subject"
    ],
    "tests.test_crypto.TestX509.test_set_subject_wrong_args": [
        "src.OpenSSL.crypto.X509.set_subject"
    ],
    "tests.test_crypto.TestX509.test_set_version_wrong_args": [
        "src.OpenSSL.crypto.X509.set_version"
    ],
    "tests.test_crypto.TestX509.test_sign_bad_pubkey_type": [
        "src.OpenSSL.crypto.X509.sign"
    ],
    "tests.test_crypto.TestX509.test_subject_name_hash": [
        "src.OpenSSL.crypto.X509.subject_name_hash"
    ],
    "tests.test_crypto.TestX509.test_type": [
        "src.OpenSSL.crypto.X509.__init__"
    ],
    "tests.test_crypto.TestX509.test_version": [
        "src.OpenSSL.crypto.X509.get_version"
    ],
    "tests.test_crypto.TestX509Ext.test_construction": [
        "src.OpenSSL.crypto.X509Extension.__init__"
    ],
    "tests.test_crypto.TestX509Ext.test_get_critical": [
        "src.OpenSSL.crypto.X509Extension.get_critical"
    ],
    "tests.test_crypto.TestX509Ext.test_get_data": [
        "src.OpenSSL.crypto.X509Extension.get_data"
    ],
    "tests.test_crypto.TestX509Ext.test_get_short_name": [
        "src.OpenSSL.crypto.X509Extension.get_short_name"
    ],
    "tests.test_crypto.TestX509Ext.test_invalid_extension": [
        "src.OpenSSL.crypto.X509Extension.__init__"
    ],
    "tests.test_crypto.TestX509Ext.test_invalid_issuer": [
        "src.OpenSSL.crypto.X509Extension.__init__"
    ],
    "tests.test_crypto.TestX509Ext.test_invalid_subject": [
        "src.OpenSSL.crypto.X509Extension.__init__"
    ],
    "tests.test_crypto.TestX509Ext.test_issuer": [
        "src.OpenSSL.crypto.dump_certificate",
        "src.OpenSSL.crypto.X509.sign"
    ],
    "tests.test_crypto.TestX509Ext.test_missing_issuer": [
        "src.OpenSSL.crypto.X509Extension.__init__"
    ],
    "tests.test_crypto.TestX509Ext.test_missing_subject": [
        "src.OpenSSL.crypto.X509Extension.__init__"
    ],
    "tests.test_crypto.TestX509Ext.test_str": [
        "src.OpenSSL.crypto.X509Extension.__str__"
    ],
    "tests.test_crypto.TestX509Ext.test_subject": [
        "src.OpenSSL.crypto.dump_certificate"
    ],
    "tests.test_crypto.TestX509Ext.test_type": [
        "src.OpenSSL.crypto.X509Extension.__init__"
    ],
    "tests.test_crypto.TestX509Ext.test_unused_issuer": [
        "src.OpenSSL.crypto.dump_certificate"
    ],
    "tests.test_crypto.TestX509Ext.test_unused_subject": [
        "src.OpenSSL.crypto.dump_certificate"
    ],
    "tests.test_crypto.TestX509Name.test_attributes": [
        "src.OpenSSL.crypto.X509Name.__getattr__",
        "src.OpenSSL.crypto.X509Name.__setattr__"
    ],
    "tests.test_crypto.TestX509Name.test_comparison": [
        "src.OpenSSL.crypto.X509.__init__",
        "src.OpenSSL.crypto.X509Name.__lt__"
    ],
    "tests.test_crypto.TestX509Name.test_copy": [
        "src.OpenSSL._util.make_assert.<locals>.openssl_assert",
        "src.OpenSSL.crypto.X509Name.__init__",
        "src.OpenSSL.crypto.X509Name.__getattr__",
        "src.OpenSSL.crypto.X509Name.__setattr__"
    ],
    "tests.test_crypto.TestX509Name.test_der": [
        "src.OpenSSL.crypto.X509Name.der"
    ],
    "tests.test_crypto.TestX509Name.test_get_components": [
        "src.OpenSSL.crypto.X509Name.get_components"
    ],
    "tests.test_crypto.TestX509Name.test_hash": [
        "src.OpenSSL.crypto.X509Name.hash"
    ],
    "tests.test_crypto.TestX509Name.test_load_nul_byte_attribute": [
        "src.OpenSSL.crypto.X509Name.__getattr__",
        "src.OpenSSL.crypto.X509.get_subject",
        "src.OpenSSL.crypto.load_certificate"
    ],
    "tests.test_crypto.TestX509Name.test_load_nul_byte_components": [
        "src.OpenSSL.crypto.X509Name.get_components"
    ],
    "tests.test_crypto.TestX509Name.test_only_string_attributes": [
        "src.OpenSSL.crypto.X509.__init__"
    ],
    "tests.test_crypto.TestX509Name.test_repr": [
        "src.OpenSSL.crypto.X509Name.__repr__"
    ],
    "tests.test_crypto.TestX509Name.test_set_attribute_failure": [
        "src.OpenSSL.crypto.X509Name.__setattr__"
    ],
    "tests.test_crypto.TestX509Name.test_set_invalid_attribute": [
        "src.OpenSSL.crypto.X509Name.__setattr__"
    ],
    "tests.test_crypto.TestX509Name.test_type": [
        "src.OpenSSL.crypto.X509.get_subject"
    ],
    "tests.test_crypto.TestX509Req.test_add_extensions": [
        "src.OpenSSL.crypto.X509Req.add_extensions"
    ],
    "tests.test_crypto.TestX509Req.test_add_extensions_wrong_args": [
        "src.OpenSSL.crypto.X509Req.add_extensions"
    ],
    "tests.test_crypto.TestX509Req.test_construction": [
        "src.OpenSSL.crypto.X509Req.__init__"
    ],
    "tests.test_crypto.TestX509Req.test_convert_from_cryptography": [
        "src.OpenSSL.crypto.X509Req.from_cryptography"
    ],
    "tests.test_crypto.TestX509Req.test_convert_from_cryptography_unsupported_type": [
        "src.OpenSSL.crypto.X509Req.from_cryptography"
    ],
    "tests.test_crypto.TestX509Req.test_convert_to_cryptography_key": [
        "src.OpenSSL.crypto.X509Req.to_cryptography"
    ],
    "tests.test_crypto.TestX509Req.test_get_extensions": [
        "src.OpenSSL.crypto.X509Req.get_extensions"
    ],
    "tests.test_crypto.TestX509Req.test_get_subject": [
        "src.OpenSSL.crypto.X509Req.get_subject"
    ],
    "tests.test_crypto.TestX509Req.test_type": [
        "src.OpenSSL.crypto.X509Req.__init__"
    ],
    "tests.test_crypto.TestX509Req.test_undef_oid": [
        "src.OpenSSL.crypto.X509Extension.get_short_name"
    ],
    "tests.test_crypto.TestX509Req.test_verify_success": [
        "src.OpenSSL.crypto.X509Req.verify"
    ],
    "tests.test_crypto.TestX509Req.test_verify_uninitialized_key": [
        "src.OpenSSL.crypto.X509Req.verify"
    ],
    "tests.test_crypto.TestX509Req.test_verify_wrong_args": [
        "src.OpenSSL.crypto.X509Req.verify"
    ],
    "tests.test_crypto.TestX509Req.test_verify_wrong_key": [
        "src.OpenSSL.crypto.X509Req.verify"
    ],
    "tests.test_crypto.TestX509Req.test_version": [
        "src.OpenSSL.crypto.X509Req.get_version"
    ],
    "tests.test_crypto.TestX509Req.test_version_wrong_args": [
        "src.OpenSSL.crypto.X509Req.set_version"
    ],
    "tests.test_crypto.TestX509Store.test_add_cert": [
        "src.OpenSSL.crypto.X509Store.add_cert"
    ],
    "tests.test_crypto.TestX509Store.test_add_cert_accepts_duplicate": [
        "src.OpenSSL.crypto.X509Store.add_cert"
    ],
    "tests.test_crypto.TestX509Store.test_add_cert_wrong_args": [
        "src.OpenSSL.crypto.X509Store.add_cert"
    ],
    "tests.test_crypto.TestX509Store.test_load_locations_fails_when_all_args_are_none": [
        "src.OpenSSL.crypto.X509Store.load_locations"
    ],
    "tests.test_crypto.TestX509Store.test_load_locations_parameters": [
        "src.OpenSSL.crypto.X509Store.load_locations"
    ],
    "tests.test_crypto.TestX509Store.test_load_locations_raises_error_on_failure": [
        "src.OpenSSL.crypto.X509Store.load_locations"
    ],
    "tests.test_crypto.TestX509Store.test_type": [
        "src.OpenSSL.crypto.X509Store.__init__"
    ],
    "tests.test_crypto.TestX509StoreContext.test_chain_reference": [
        "src.OpenSSL.crypto.X509StoreContext.verify_certificate"
    ],
    "tests.test_crypto.TestX509StoreContext.test_failure_building_untrusted_chain_raises": [
        "src.OpenSSL.crypto.X509StoreContext._build_certificate_stack.<locals>.cleanup",
        "src.OpenSSL.crypto.X509StoreContext.__init__",
        "src.OpenSSL.crypto.X509Store.__init__",
        "src.OpenSSL.crypto.X509Store.add_cert"
    ],
    "tests.test_crypto.TestX509StoreContext.test_get_verified_chain": [
        "src.OpenSSL.crypto.X509StoreContext.get_verified_chain"
    ],
    "tests.test_crypto.TestX509StoreContext.test_get_verified_chain_invalid_chain_no_root": [
        "src.OpenSSL.crypto.X509StoreContext.get_verified_chain"
    ],
    "tests.test_crypto.TestX509StoreContext.test_invalid_chain_no_intermediate": [
        "src.OpenSSL.crypto.X509StoreContext.verify_certificate",
        "src.OpenSSL.crypto.X509Name.__getattr__",
        "src.OpenSSL.crypto.X509Store.add_cert",
        "src.OpenSSL.crypto.X509StoreContext.__init__",
        "src.OpenSSL.crypto.X509Store.__init__"
    ],
    "tests.test_crypto.TestX509StoreContext.test_invalid_chain_no_root": [
        "src.OpenSSL.crypto.X509Store.add_cert",
        "src.OpenSSL.crypto.X509Name.__getattr__",
        "src.OpenSSL.crypto.X509StoreContext.__init__",
        "src.OpenSSL.crypto.X509Store.__init__",
        "src.OpenSSL.crypto.X509StoreContext.verify_certificate"
    ],
    "tests.test_crypto.TestX509StoreContext.test_modification_pre_verify": [
        "src.OpenSSL.crypto.X509StoreContext.verify_certificate",
        "src.OpenSSL.crypto.X509Name.__getattr__",
        "src.OpenSSL.crypto.X509StoreContext.set_store"
    ],
    "tests.test_crypto.TestX509StoreContext.test_reuse": [
        "src.OpenSSL.crypto.X509StoreContext.verify_certificate"
    ],
    "tests.test_crypto.TestX509StoreContext.test_trusted_self_signed": [
        "src.OpenSSL.crypto.X509StoreContext.verify_certificate"
    ],
    "tests.test_crypto.TestX509StoreContext.test_untrusted_chain_wrong_args": [
        "src.OpenSSL.crypto.X509StoreContext.__init__",
        "src.OpenSSL.crypto.X509Store.__init__",
        "src.OpenSSL.crypto.X509StoreContext._build_certificate_stack.<locals>.cleanup",
        "src.OpenSSL.crypto.X509Store.add_cert"
    ],
    "tests.test_crypto.TestX509StoreContext.test_untrusted_self_signed": [
        "src.OpenSSL.crypto.X509Name.__getattr__",
        "src.OpenSSL.crypto.X509.get_subject",
        "src.OpenSSL.crypto.X509StoreContext.verify_certificate"
    ],
    "tests.test_crypto.TestX509StoreContext.test_valid": [
        "src.OpenSSL.crypto.X509StoreContext.verify_certificate",
        "src.OpenSSL.crypto.X509Store.add_cert"
    ],
    "tests.test_crypto.TestX509StoreContext.test_valid_untrusted_chain_reuse": [
        "src.OpenSSL.crypto.X509StoreContext.verify_certificate"
    ],
    "tests.test_crypto.TestX509StoreContext.test_verify_fail_with_chain": [
        "src.OpenSSL.crypto.X509StoreContext.verify_certificate"
    ],
    "tests.test_crypto.TestX509StoreContext.test_verify_failure_with_empty_ca_directory": [
        "src.OpenSSL.crypto.X509StoreContext.verify_certificate"
    ],
    "tests.test_crypto.TestX509StoreContext.test_verify_success_with_chain": [
        "src.OpenSSL.crypto.X509StoreContext.verify_certificate"
    ],
    "tests.test_crypto.TestX509StoreContext.test_verify_with_ca_file_location": [
        "src.OpenSSL.crypto.X509StoreContext.verify_certificate",
        "src.OpenSSL.crypto.X509Store.load_locations"
    ],
    "tests.test_crypto.TestX509StoreContext.test_verify_with_ca_path_location": [
        "src.OpenSSL.crypto.X509Store.load_locations",
        "src.OpenSSL.crypto.X509StoreContext.verify_certificate"
    ],
    "tests.test_crypto.TestX509StoreContext.test_verify_with_cafile_and_capath": [
        "src.OpenSSL.crypto.X509StoreContext.verify_certificate"
    ],
    "tests.test_crypto.TestX509StoreContext.test_verify_with_multiple_ca_files": [
        "src.OpenSSL.crypto.X509StoreContext.verify_certificate",
        "src.OpenSSL.crypto.X509Store.load_locations"
    ],
    "tests.test_crypto.TestX509StoreContext.test_verify_with_partial_chain": [
        "src.OpenSSL.crypto.X509StoreContext.verify_certificate"
    ],
    "tests.test_crypto.TestX509StoreContext.test_verify_with_time": [
        "src.OpenSSL.crypto.X509Store.set_time"
    ],
    "tests.test_crypto._PKeyInteractionTestsMixin.test_sign": [
        "src.OpenSSL.crypto.NetscapeSPKI.sign",
        "src.OpenSSL.crypto.X509Req.sign",
        "src.OpenSSL.crypto.X509.sign"
    ],
    "tests.test_crypto._PKeyInteractionTestsMixin.test_sign_with_public_key": [
        "src.OpenSSL.crypto.NetscapeSPKI.get_pubkey",
        "src.OpenSSL.crypto.X509Req.get_pubkey",
        "src.OpenSSL.crypto.NetscapeSPKI.set_pubkey",
        "src.OpenSSL.crypto.X509.get_pubkey",
        "src.OpenSSL.crypto.X509Req.set_pubkey",
        "src.OpenSSL.crypto.NetscapeSPKI.sign",
        "src.OpenSSL.crypto.X509Req.sign",
        "src.OpenSSL.crypto.X509.set_pubkey",
        "src.OpenSSL.crypto.X509.sign"
    ],
    "tests.test_crypto._PKeyInteractionTestsMixin.test_sign_with_ungenerated": [
        "src.OpenSSL.crypto.NetscapeSPKI.sign",
        "src.OpenSSL.crypto.X509Req.sign",
        "src.OpenSSL.crypto.X509.sign"
    ],
    "tests.test_crypto._PKeyInteractionTestsMixin.test_sign_with_unknown_digest": [
        "src.OpenSSL.crypto.NetscapeSPKI.sign",
        "src.OpenSSL.crypto.X509Req.sign",
        "src.OpenSSL.crypto.X509.sign",
        "src.OpenSSL.crypto.PKey.__init__"
    ],
    "tests.test_debug.test_debug_info": [],
    "tests.test_rand.TestRand.test_add": [
        "src.OpenSSL.rand.add"
    ],
    "tests.test_rand.TestRand.test_add_wrong_args": [
        "src.OpenSSL.rand.add"
    ],
    "tests.test_rand.TestRand.test_status": [
        "src.OpenSSL.rand.status"
    ],
    "tests.test_ssl.TestApplicationLayerProtoNegotiation.test_alpn_call_failure": [
        "src.OpenSSL.SSL.Context.set_alpn_protos"
    ],
    "tests.test_ssl.TestApplicationLayerProtoNegotiation.test_alpn_callback_exception": [
        "src.OpenSSL.SSL.Context.set_alpn_select_callback",
        "src.OpenSSL.SSL.Context.set_alpn_protos"
    ],
    "tests.test_ssl.TestApplicationLayerProtoNegotiation.test_alpn_no_server": [
        "src.OpenSSL.SSL.Connection.get_alpn_proto_negotiated"
    ],
    "tests.test_ssl.TestApplicationLayerProtoNegotiation.test_alpn_no_server_overlap": [
        "src.OpenSSL.SSL.Connection.get_alpn_proto_negotiated",
        "src.OpenSSL.SSL.Context.set_alpn_select_callback"
    ],
    "tests.test_ssl.TestApplicationLayerProtoNegotiation.test_alpn_select_cb_returns_invalid_value": [
        "src.OpenSSL.SSL.Connection.get_alpn_proto_negotiated",
        "src.OpenSSL.SSL.Context.set_alpn_select_callback"
    ],
    "tests.test_ssl.TestApplicationLayerProtoNegotiation.test_alpn_server_fail": [
        "src.OpenSSL.SSL.Context.set_alpn_select_callback"
    ],
    "tests.test_ssl.TestApplicationLayerProtoNegotiation.test_alpn_set_on_connection": [
        "src.OpenSSL.SSL.Connection.get_alpn_proto_negotiated"
    ],
    "tests.test_ssl.TestApplicationLayerProtoNegotiation.test_alpn_success": [
        "src.OpenSSL.SSL.Connection.get_alpn_proto_negotiated",
        "src.OpenSSL.SSL.Context.set_alpn_protos",
        "src.OpenSSL.SSL.Context.set_alpn_select_callback"
    ],
    "tests.test_ssl.TestConnection.test_accept": [
        "src.OpenSSL.SSL.Connection.accept"
    ],
    "tests.test_ssl.TestConnection.test_app_data": [
        "src.OpenSSL.SSL.Connection.get_app_data"
    ],
    "tests.test_ssl.TestConnection.test_bio_read_wrong_args": [
        "src.OpenSSL.SSL.Connection.bio_read"
    ],
    "tests.test_ssl.TestConnection.test_bio_write": [
        "src.OpenSSL.SSL.Connection.bio_write"
    ],
    "tests.test_ssl.TestConnection.test_bio_write_wrong_args": [
        "src.OpenSSL.SSL.Connection.bio_write"
    ],
    "tests.test_ssl.TestConnection.test_buffer_size": [
        "src.OpenSSL.SSL.Connection.bio_read"
    ],
    "tests.test_ssl.TestConnection.test_client_get_session": [
        "src.OpenSSL.SSL.Connection.get_session"
    ],
    "tests.test_ssl.TestConnection.test_client_set_session": [
        "src.OpenSSL.SSL.Connection.get_session",
        "src.OpenSSL.SSL.Context.set_session_id"
    ],
    "tests.test_ssl.TestConnection.test_connect": [
        "src.OpenSSL.SSL.Connection.connect"
    ],
    "tests.test_ssl.TestConnection.test_connect_ex": [
        "src.OpenSSL.SSL.Connection.connect_ex"
    ],
    "tests.test_ssl.TestConnection.test_connect_refused": [
        "src.OpenSSL.SSL.Connection.connect"
    ],
    "tests.test_ssl.TestConnection.test_connect_wrong_args": [
        "src.OpenSSL.SSL.Connection.connect"
    ],
    "tests.test_ssl.TestConnection.test_get_certificate": [
        "src.OpenSSL.SSL.Connection.get_certificate"
    ],
    "tests.test_ssl.TestConnection.test_get_certificate_none": [
        "src.OpenSSL.SSL.Connection.get_certificate"
    ],
    "tests.test_ssl.TestConnection.test_get_cipher_bits": [
        "src.OpenSSL.SSL.Connection.get_cipher_bits"
    ],
    "tests.test_ssl.TestConnection.test_get_cipher_bits_before_connect": [
        "src.OpenSSL.SSL.Connection.get_cipher_bits"
    ],
    "tests.test_ssl.TestConnection.test_get_cipher_name": [
        "src.OpenSSL.SSL.Connection.get_cipher_name"
    ],
    "tests.test_ssl.TestConnection.test_get_cipher_name_before_connect": [
        "src.OpenSSL.SSL.Connection.get_cipher_name"
    ],
    "tests.test_ssl.TestConnection.test_get_cipher_version": [
        "src.OpenSSL.SSL.Connection.get_cipher_version"
    ],
    "tests.test_ssl.TestConnection.test_get_cipher_version_before_connect": [
        "src.OpenSSL.SSL.Connection.get_cipher_version"
    ],
    "tests.test_ssl.TestConnection.test_get_context": [
        "src.OpenSSL.SSL.Connection.get_context"
    ],
    "tests.test_ssl.TestConnection.test_get_finished": [
        "src.OpenSSL.SSL.Connection.get_finished"
    ],
    "tests.test_ssl.TestConnection.test_get_finished_before_connect": [
        "src.OpenSSL.SSL.Connection.get_finished"
    ],
    "tests.test_ssl.TestConnection.test_get_peer_cert_chain": [
        "src.OpenSSL.SSL.Connection.get_peer_cert_chain"
    ],
    "tests.test_ssl.TestConnection.test_get_peer_cert_chain_none": [
        "src.OpenSSL.SSL.Connection.get_peer_cert_chain"
    ],
    "tests.test_ssl.TestConnection.test_get_peer_finished": [
        "src.OpenSSL.SSL.Connection.get_peer_finished"
    ],
    "tests.test_ssl.TestConnection.test_get_peer_finished_before_connect": [
        "src.OpenSSL.SSL.Connection.get_peer_finished"
    ],
    "tests.test_ssl.TestConnection.test_get_protocol_version": [
        "src.OpenSSL.SSL.Connection.get_protocol_version"
    ],
    "tests.test_ssl.TestConnection.test_get_protocol_version_name": [
        "src.OpenSSL.SSL.Connection.get_protocol_version_name"
    ],
    "tests.test_ssl.TestConnection.test_get_session_unconnected": [
        "src.OpenSSL.SSL.Connection.get_session"
    ],
    "tests.test_ssl.TestConnection.test_get_verified_chain": [
        "src.OpenSSL.SSL.Connection.get_verified_chain"
    ],
    "tests.test_ssl.TestConnection.test_get_verified_chain_none": [
        "src.OpenSSL.SSL.Connection.get_verified_chain"
    ],
    "tests.test_ssl.TestConnection.test_get_verified_chain_unconnected": [
        "src.OpenSSL.SSL.Connection.get_verified_chain"
    ],
    "tests.test_ssl.TestConnection.test_makefile": [
        "src.OpenSSL.SSL.Connection.makefile"
    ],
    "tests.test_ssl.TestConnection.test_peek": [
        "src.OpenSSL.SSL.Connection.recv"
    ],
    "tests.test_ssl.TestConnection.test_pending": [
        "src.OpenSSL.SSL.Connection.pending"
    ],
    "tests.test_ssl.TestConnection.test_server_get_session": [
        "src.OpenSSL.SSL.Connection.get_session"
    ],
    "tests.test_ssl.TestConnection.test_set_context": [
        "src.OpenSSL.SSL.Connection.set_context"
    ],
    "tests.test_ssl.TestConnection.test_set_context_wrong_args": [
        "src.OpenSSL.SSL.Connection.set_context"
    ],
    "tests.test_ssl.TestConnection.test_set_session_wrong_args": [
        "src.OpenSSL.SSL.Connection.set_session"
    ],
    "tests.test_ssl.TestConnection.test_set_session_wrong_method": [
        "src.OpenSSL.SSL.Context.set_session_id",
        "src.OpenSSL.SSL.Connection.get_session"
    ],
    "tests.test_ssl.TestConnection.test_set_shutdown": [
        "src.OpenSSL.SSL.Connection.set_shutdown"
    ],
    "tests.test_ssl.TestConnection.test_set_tlsext_host_name_wrong_args": [
        "src.OpenSSL.SSL.Connection.set_tlsext_host_name"
    ],
    "tests.test_ssl.TestConnection.test_set_verify_callback_reference": [
        "src.OpenSSL.SSL.Connection.set_verify"
    ],
    "tests.test_ssl.TestConnection.test_set_verify_overrides_context": [
        "src.OpenSSL.SSL.Connection.set_verify",
        "src.OpenSSL.SSL.Connection.get_verify_mode",
        "src.OpenSSL.SSL.Context.get_verify_mode"
    ],
    "tests.test_ssl.TestConnection.test_shutdown": [
        "src.OpenSSL.SSL.Connection.shutdown"
    ],
    "tests.test_ssl.TestConnection.test_shutdown_closed": [
        "src.OpenSSL.SSL.Connection.shutdown"
    ],
    "tests.test_ssl.TestConnection.test_shutdown_truncated": [
        "src.OpenSSL.SSL.Connection.shutdown"
    ],
    "tests.test_ssl.TestConnection.test_shutdown_wrong_args": [
        "src.OpenSSL.SSL.Connection.set_shutdown"
    ],
    "tests.test_ssl.TestConnection.test_state_string": [
        "src.OpenSSL.SSL.Connection.get_state_string"
    ],
    "tests.test_ssl.TestConnection.test_tls_finished_message_symmetry": [
        "src.OpenSSL.SSL.Connection.get_peer_finished",
        "src.OpenSSL.SSL.Connection.get_finished"
    ],
    "tests.test_ssl.TestConnection.test_type": [
        "src.OpenSSL.SSL.Context.__init__"
    ],
    "tests.test_ssl.TestConnection.test_wantReadError": [
        "src.OpenSSL.SSL.Connection.bio_read"
    ],
    "tests.test_ssl.TestConnection.test_wantWriteError": [
        "src.OpenSSL.SSL.Connection.__init__",
        "src.OpenSSL.SSL.Context.__init__",
        "src.OpenSSL.SSL.Connection.set_connect_state",
        "src.OpenSSL.SSL.Connection.do_handshake"
    ],
    "tests.test_ssl.TestConnection.test_wrong_args": [
        "src.OpenSSL.SSL.Connection.__init__"
    ],
    "tests.test_ssl.TestConnectionGetCipherList.test_result": [
        "src.OpenSSL.SSL.Connection.get_cipher_list"
    ],
    "tests.test_ssl.TestConnectionRecvInto.test_bytearray_doesnt_overfill": [
        "src.OpenSSL.SSL.Connection.recv_into"
    ],
    "tests.test_ssl.TestConnectionRecvInto.test_bytearray_no_length": [
        "src.OpenSSL.SSL.Connection.recv_into"
    ],
    "tests.test_ssl.TestConnectionRecvInto.test_bytearray_really_doesnt_overfill": [
        "src.OpenSSL.SSL.Connection.recv_into"
    ],
    "tests.test_ssl.TestConnectionRecvInto.test_bytearray_respects_length": [
        "src.OpenSSL.SSL.Connection.recv_into"
    ],
    "tests.test_ssl.TestConnectionRecvInto.test_memoryview_doesnt_overfill": [
        "src.OpenSSL.SSL.Connection.recv_into"
    ],
    "tests.test_ssl.TestConnectionRecvInto.test_memoryview_no_length": [
        "src.OpenSSL.SSL.Connection.recv_into"
    ],
    "tests.test_ssl.TestConnectionRecvInto.test_memoryview_really_doesnt_overfill": [
        "src.OpenSSL.SSL.Connection.recv_into"
    ],
    "tests.test_ssl.TestConnectionRecvInto.test_memoryview_respects_length": [
        "src.OpenSSL.SSL.Connection.recv_into"
    ],
    "tests.test_ssl.TestConnectionRecvInto.test_peek": [
        "src.OpenSSL.SSL.Connection.recv_into",
        "src.OpenSSL.SSL.Connection.send"
    ],
    "tests.test_ssl.TestConnectionRenegotiate.test_renegotiate": [
        "src.OpenSSL.SSL.Connection.renegotiate"
    ],
    "tests.test_ssl.TestConnectionRenegotiate.test_total_renegotiations": [
        "src.OpenSSL.SSL.Connection.total_renegotiations"
    ],
    "tests.test_ssl.TestConnectionSend.test_buf_too_large": [
        "src.OpenSSL.SSL.Connection.__init__",
        "src.OpenSSL.SSL.Context.__init__",
        "src.OpenSSL.SSL.Connection.send"
    ],
    "tests.test_ssl.TestConnectionSend.test_short_bytearray": [
        "src.OpenSSL.SSL.Connection.send",
        "src.OpenSSL.SSL.Connection.recv"
    ],
    "tests.test_ssl.TestConnectionSend.test_short_bytes": [
        "src.OpenSSL.SSL.Connection.send",
        "src.OpenSSL.SSL.Connection.recv"
    ],
    "tests.test_ssl.TestConnectionSend.test_short_memoryview": [
        "src.OpenSSL.SSL.Connection.recv",
        "src.OpenSSL.SSL.Connection.send"
    ],
    "tests.test_ssl.TestConnectionSend.test_text": [
        "src.OpenSSL.SSL.Connection.send",
        "src.OpenSSL.SSL.Connection.recv"
    ],
    "tests.test_ssl.TestConnectionSend.test_wrong_args": [
        "src.OpenSSL.SSL.Connection.send"
    ],
    "tests.test_ssl.TestConnectionSendall.test_closed": [
        "src.OpenSSL.SSL.Connection.sendall",
        "src.OpenSSL.SSL.Connection.sock_shutdown"
    ],
    "tests.test_ssl.TestConnectionSendall.test_long": [
        "src.OpenSSL.SSL.Connection.sendall"
    ],
    "tests.test_ssl.TestConnectionSendall.test_short": [
        "src.OpenSSL.SSL.Connection.sendall",
        "src.OpenSSL.SSL.Connection.recv"
    ],
    "tests.test_ssl.TestConnectionSendall.test_short_memoryview": [
        "src.OpenSSL.SSL.Connection.recv"
    ],
    "tests.test_ssl.TestConnectionSendall.test_text": [
        "src.OpenSSL.SSL.Connection.recv",
        "src.OpenSSL.SSL.Connection.sendall"
    ],
    "tests.test_ssl.TestConnectionSendall.test_wrong_args": [
        "src.OpenSSL.SSL.Connection.sendall"
    ],
    "tests.test_ssl.TestConstants.test_op_cookie_exchange": [],
    "tests.test_ssl.TestConstants.test_op_no_compression": [],
    "tests.test_ssl.TestConstants.test_op_no_query_mtu": [],
    "tests.test_ssl.TestConstants.test_op_no_ticket": [],
    "tests.test_ssl.TestConstants.test_sess_cache_both": [],
    "tests.test_ssl.TestConstants.test_sess_cache_client": [],
    "tests.test_ssl.TestConstants.test_sess_cache_no_auto_clear": [],
    "tests.test_ssl.TestConstants.test_sess_cache_no_internal": [],
    "tests.test_ssl.TestConstants.test_sess_cache_no_internal_lookup": [],
    "tests.test_ssl.TestConstants.test_sess_cache_no_internal_store": [],
    "tests.test_ssl.TestConstants.test_sess_cache_off": [],
    "tests.test_ssl.TestConstants.test_sess_cache_server": [],
    "tests.test_ssl.TestContext.test_add_extra_chain_cert": [
        "src.OpenSSL.SSL.Context.add_extra_chain_cert"
    ],
    "tests.test_ssl.TestContext.test_add_extra_chain_cert_invalid_cert": [
        "src.OpenSSL.SSL.Context.add_extra_chain_cert"
    ],
    "tests.test_ssl.TestContext.test_app_data": [
        "src.OpenSSL.SSL.Context.get_app_data",
        "src.OpenSSL.SSL.Context.set_app_data"
    ],
    "tests.test_ssl.TestContext.test_check_env_vars": [
        "src.OpenSSL.SSL.Context._check_env_vars_set"
    ],
    "tests.test_ssl.TestContext.test_check_privatekey_invalid": [
        "src.OpenSSL.SSL.Context.check_privatekey"
    ],
    "tests.test_ssl.TestContext.test_check_privatekey_valid": [
        "src.OpenSSL.SSL.Context.check_privatekey"
    ],
    "tests.test_ssl.TestContext.test_fallback_default_verify_paths": [
        "src.OpenSSL.SSL.Context.set_default_verify_paths"
    ],
    "tests.test_ssl.TestContext.test_fallback_path_is_not_file_or_dir": [
        "src.OpenSSL.SSL.Context._fallback_default_verify_paths"
    ],
    "tests.test_ssl.TestContext.test_get_cert_store": [
        "src.OpenSSL.SSL.Context.get_cert_store"
    ],
    "tests.test_ssl.TestContext.test_load_client_ca": [
        "src.OpenSSL.SSL.Context.load_client_ca"
    ],
    "tests.test_ssl.TestContext.test_load_client_ca_invalid": [
        "src.OpenSSL.SSL.Context.load_client_ca"
    ],
    "tests.test_ssl.TestContext.test_load_client_ca_unicode": [
        "src.OpenSSL.SSL.Context.load_client_ca"
    ],
    "tests.test_ssl.TestContext.test_load_tmp_dh_bytes": [
        "src.OpenSSL.SSL.Context.load_tmp_dh"
    ],
    "tests.test_ssl.TestContext.test_load_tmp_dh_missing_file": [
        "src.OpenSSL.SSL.Context.load_tmp_dh"
    ],
    "tests.test_ssl.TestContext.test_load_tmp_dh_unicode": [
        "src.OpenSSL.SSL.Context.load_tmp_dh"
    ],
    "tests.test_ssl.TestContext.test_load_tmp_dh_wrong_args": [
        "src.OpenSSL.SSL.Context.load_tmp_dh"
    ],
    "tests.test_ssl.TestContext.test_load_verify_bytes_cafile": [
        "src.OpenSSL.SSL.Context.load_verify_locations"
    ],
    "tests.test_ssl.TestContext.test_load_verify_directory_capath": [
        "src.OpenSSL.SSL.Context.load_verify_locations",
        "src.OpenSSL.SSL.Connection.get_peer_certificate"
    ],
    "tests.test_ssl.TestContext.test_load_verify_invalid_file": [
        "src.OpenSSL.SSL.Context.load_verify_locations"
    ],
    "tests.test_ssl.TestContext.test_load_verify_locations_wrong_args": [
        "src.OpenSSL.SSL.Context.load_verify_locations"
    ],
    "tests.test_ssl.TestContext.test_load_verify_unicode_cafile": [
        "src.OpenSSL.SSL.Context.load_verify_locations"
    ],
    "tests.test_ssl.TestContext.test_method": [
        "src.OpenSSL.SSL.Context.set_mode",
        "src.OpenSSL.SSL.Context.__init__"
    ],
    "tests.test_ssl.TestContext.test_passwd_callback_exception": [
        "src.OpenSSL.SSL.Context.set_passwd_cb"
    ],
    "tests.test_ssl.TestContext.test_passwd_callback_false": [
        "src.OpenSSL.SSL.Context.set_passwd_cb",
        "src.OpenSSL.SSL.Context.use_privatekey_file"
    ],
    "tests.test_ssl.TestContext.test_passwd_callback_non_string": [
        "src.OpenSSL.SSL.Context.set_passwd_cb"
    ],
    "tests.test_ssl.TestContext.test_passwd_callback_too_long": [
        "src.OpenSSL.SSL.Context.set_passwd_cb"
    ],
    "tests.test_ssl.TestContext.test_session_cache_mode": [
        "src.OpenSSL.SSL.Context.set_session_cache_mode",
        "src.OpenSSL.SSL.Context.get_session_cache_mode"
    ],
    "tests.test_ssl.TestContext.test_set_cipher_list": [
        "src.OpenSSL.SSL.Context.set_cipher_list",
        "src.OpenSSL.SSL.Connection.get_cipher_list"
    ],
    "tests.test_ssl.TestContext.test_set_cipher_list_no_cipher_match": [
        "src.OpenSSL.SSL.Context.set_cipher_list"
    ],
    "tests.test_ssl.TestContext.test_set_cipher_list_wrong_type": [
        "src.OpenSSL.SSL.Context.set_cipher_list"
    ],
    "tests.test_ssl.TestContext.test_set_default_verify_paths": [
        "src.OpenSSL.SSL.Context.set_default_verify_paths"
    ],
    "tests.test_ssl.TestContext.test_set_info_callback": [
        "src.OpenSSL.SSL.Context.set_info_callback"
    ],
    "tests.test_ssl.TestContext.test_set_keylog_callback": [
        "src.OpenSSL.SSL.Context.set_keylog_callback"
    ],
    "tests.test_ssl.TestContext.test_set_mode": [
        "src.OpenSSL.SSL.Context.set_mode"
    ],
    "tests.test_ssl.TestContext.test_set_mode_wrong_args": [
        "src.OpenSSL.SSL.Context.set_mode"
    ],
    "tests.test_ssl.TestContext.test_set_options": [
        "src.OpenSSL.SSL.Context.set_options"
    ],
    "tests.test_ssl.TestContext.test_set_options_wrong_args": [
        "src.OpenSSL.SSL.Context.set_options"
    ],
    "tests.test_ssl.TestContext.test_set_passwd_cb": [
        "src.OpenSSL.SSL.Context.set_passwd_cb"
    ],
    "tests.test_ssl.TestContext.test_set_passwd_cb_wrong_args": [
        "src.OpenSSL.SSL.Context.set_passwd_cb"
    ],
    "tests.test_ssl.TestContext.test_set_proto_version": [
        "src.OpenSSL.SSL.Context.set_max_proto_version"
    ],
    "tests.test_ssl.TestContext.test_set_session_cache_mode_wrong_args": [
        "src.OpenSSL.SSL.Context.set_session_cache_mode"
    ],
    "tests.test_ssl.TestContext.test_set_session_id": [
        "src.OpenSSL.SSL.Context.set_session_id"
    ],
    "tests.test_ssl.TestContext.test_set_session_id_fail": [
        "src.OpenSSL.SSL.Context.set_session_id"
    ],
    "tests.test_ssl.TestContext.test_set_session_id_unicode": [
        "src.OpenSSL.SSL.Context.set_session_id"
    ],
    "tests.test_ssl.TestContext.test_set_timeout_wrong_args": [
        "src.OpenSSL.SSL.Context.set_timeout"
    ],
    "tests.test_ssl.TestContext.test_set_tlsext_use_srtp_invalid_profile": [
        "src.OpenSSL.SSL.Context.set_tlsext_use_srtp"
    ],
    "tests.test_ssl.TestContext.test_set_tlsext_use_srtp_not_bytes": [
        "src.OpenSSL.SSL.Context.set_tlsext_use_srtp"
    ],
    "tests.test_ssl.TestContext.test_set_tlsext_use_srtp_valid": [
        "src.OpenSSL.SSL.Context.set_tlsext_use_srtp"
    ],
    "tests.test_ssl.TestContext.test_set_tmp_ecdh": [
        "src.OpenSSL.SSL.Context.set_tmp_ecdh"
    ],
    "tests.test_ssl.TestContext.test_set_verify_callback_connection_argument": [
        "src.OpenSSL.SSL.Context.set_verify"
    ],
    "tests.test_ssl.TestContext.test_set_verify_callback_exception": [
        "src.OpenSSL.SSL.Context.set_verify"
    ],
    "tests.test_ssl.TestContext.test_set_verify_callback_reference": [
        "src.OpenSSL.SSL.Context.set_verify"
    ],
    "tests.test_ssl.TestContext.test_set_verify_default_callback": [
        "src.OpenSSL.SSL.Context.set_verify"
    ],
    "tests.test_ssl.TestContext.test_set_verify_depth_wrong_args": [
        "src.OpenSSL.SSL.Context.set_verify_depth"
    ],
    "tests.test_ssl.TestContext.test_set_verify_mode": [
        "src.OpenSSL.SSL.Context.get_verify_mode"
    ],
    "tests.test_ssl.TestContext.test_set_verify_wrong_callable_arg": [
        "src.OpenSSL.SSL.Context.set_verify"
    ],
    "tests.test_ssl.TestContext.test_set_verify_wrong_mode_arg": [
        "src.OpenSSL.SSL.Context.set_verify"
    ],
    "tests.test_ssl.TestContext.test_timeout": [
        "src.OpenSSL.SSL.Context.get_timeout"
    ],
    "tests.test_ssl.TestContext.test_type": [
        "src.OpenSSL.SSL.Context.__init__"
    ],
    "tests.test_ssl.TestContext.test_use_certificate_chain_file_bytes": [
        "src.OpenSSL.SSL.Context.use_certificate_chain_file"
    ],
    "tests.test_ssl.TestContext.test_use_certificate_chain_file_missing_file": [
        "src.OpenSSL.SSL.Context.use_certificate_chain_file"
    ],
    "tests.test_ssl.TestContext.test_use_certificate_chain_file_unicode": [
        "src.OpenSSL.SSL.Context.use_certificate_chain_file"
    ],
    "tests.test_ssl.TestContext.test_use_certificate_chain_file_wrong_args": [
        "src.OpenSSL.SSL.Context.use_certificate_chain_file"
    ],
    "tests.test_ssl.TestContext.test_use_certificate_file_bytes": [
        "src.OpenSSL.SSL.Context.use_certificate_file"
    ],
    "tests.test_ssl.TestContext.test_use_certificate_file_missing": [
        "src.OpenSSL.SSL.Context.use_certificate_file"
    ],
    "tests.test_ssl.TestContext.test_use_certificate_file_unicode": [
        "src.OpenSSL.SSL.Context.use_certificate_file"
    ],
    "tests.test_ssl.TestContext.test_use_certificate_file_wrong_args": [
        "src.OpenSSL.SSL.Context.use_certificate_file"
    ],
    "tests.test_ssl.TestContext.test_use_privatekey_file_bytes": [
        "src.OpenSSL.SSL.Context.use_privatekey_file"
    ],
    "tests.test_ssl.TestContext.test_use_privatekey_file_missing": [
        "src.OpenSSL.SSL.Context.use_privatekey_file"
    ],
    "tests.test_ssl.TestContext.test_use_privatekey_file_unicode": [
        "src.OpenSSL.SSL.Context.use_privatekey_file"
    ],
    "tests.test_ssl.TestContext.test_verify_depth": [
        "src.OpenSSL.SSL.Context.get_verify_depth"
    ],
    "tests.test_ssl.TestContext.test_verify_no_fallback_if_env_vars_set": [
        "src.OpenSSL.SSL.Context.set_default_verify_paths"
    ],
    "tests.test_ssl.TestContext.test_wrong_privatekey_file_wrong_args": [
        "src.OpenSSL.SSL.Context.use_privatekey_file"
    ],
    "tests.test_ssl.TestContext.test_x509_in_verify_works": [
        "src.OpenSSL.SSL.Context.set_verify"
    ],
    "tests.test_ssl.TestContextConnection.test_use_certificate": [
        "src.OpenSSL.SSL.Connection.use_certificate"
    ],
    "tests.test_ssl.TestContextConnection.test_use_certificate_uninitialized": [
        "src.OpenSSL.SSL.Connection.use_certificate"
    ],
    "tests.test_ssl.TestContextConnection.test_use_certificate_wrong_args": [
        "src.OpenSSL.SSL.Connection.use_certificate"
    ],
    "tests.test_ssl.TestContextConnection.test_use_privatekey": [
        "src.OpenSSL.SSL.Connection.use_privatekey"
    ],
    "tests.test_ssl.TestContextConnection.test_use_privatekey_wrong_key": [
        "src.OpenSSL.SSL.Connection.use_privatekey"
    ],
    "tests.test_ssl.TestDTLS.test_it_works_at_all": [
        "src.OpenSSL.SSL.Connection.bio_write",
        "src.OpenSSL.SSL.Connection.get_cleartext_mtu",
        "src.OpenSSL.SSL.Connection.get_selected_srtp_profile"
    ],
    "tests.test_ssl.TestDTLS.test_it_works_with_srtp": [
        "src.OpenSSL.SSL.Connection.bio_write",
        "src.OpenSSL.SSL.Connection.get_selected_srtp_profile",
        "src.OpenSSL.SSL.Connection.get_cleartext_mtu",
        "src.OpenSSL.SSL.Context.set_tlsext_use_srtp"
    ],
    "tests.test_ssl.TestDTLS.test_timeout": [
        "src.OpenSSL.SSL.Connection.DTLSv1_get_timeout",
        "src.OpenSSL.SSL.Connection.DTLSv1_handle_timeout"
    ],
    "tests.test_ssl.TestError.test_type": [],
    "tests.test_ssl.TestInfoConstants.test_integers": [],
    "tests.test_ssl.TestMemoryBIO.test_add_client_ca_wrong_args": [
        "src.OpenSSL.SSL.Context.add_client_ca"
    ],
    "tests.test_ssl.TestMemoryBIO.test_memory_connect": [
        "src.OpenSSL.SSL.Connection.server_random",
        "src.OpenSSL.SSL.Connection.export_keying_material",
        "src.OpenSSL.SSL.Connection.master_key",
        "src.OpenSSL.SSL.Connection.client_random"
    ],
    "tests.test_ssl.TestMemoryBIO.test_multiple_add_client_ca": [
        "src.OpenSSL.crypto.load_certificate",
        "src.OpenSSL.SSL.Connection.get_client_ca_list"
    ],
    "tests.test_ssl.TestMemoryBIO.test_mutated_ca_list": [
        "src.OpenSSL.SSL.Connection.get_client_ca_list"
    ],
    "tests.test_ssl.TestMemoryBIO.test_one_add_client_ca": [
        "src.OpenSSL.SSL.Connection.get_client_ca_list",
        "src.OpenSSL.crypto.load_certificate"
    ],
    "tests.test_ssl.TestMemoryBIO.test_outgoing_overflow": [
        "src.OpenSSL.SSL.Connection.send",
        "src.OpenSSL.SSL.Context.set_verify"
    ],
    "tests.test_ssl.TestMemoryBIO.test_reset_ca_list": [
        "src.OpenSSL.SSL.Connection.get_client_ca_list",
        "src.OpenSSL.crypto.X509.get_subject"
    ],
    "tests.test_ssl.TestMemoryBIO.test_set_after_add_client_ca": [
        "src.OpenSSL.SSL.Connection.get_client_ca_list",
        "src.OpenSSL.crypto.X509.get_subject",
        "src.OpenSSL.crypto.load_certificate"
    ],
    "tests.test_ssl.TestMemoryBIO.test_set_and_add_client_ca": [
        "src.OpenSSL.SSL.Connection.get_client_ca_list",
        "src.OpenSSL.crypto.load_certificate",
        "src.OpenSSL.crypto.X509.get_subject"
    ],
    "tests.test_ssl.TestMemoryBIO.test_set_client_ca_list_errors": [
        "src.OpenSSL.SSL.Context.set_client_ca_list"
    ],
    "tests.test_ssl.TestMemoryBIO.test_set_empty_ca_list": [
        "src.OpenSSL.SSL.Connection.get_client_ca_list"
    ],
    "tests.test_ssl.TestMemoryBIO.test_set_multiple_ca_list": [
        "src.OpenSSL.SSL.Connection.get_client_ca_list",
        "src.OpenSSL.crypto.X509.get_subject"
    ],
    "tests.test_ssl.TestMemoryBIO.test_set_one_ca_list": [
        "src.OpenSSL.SSL.Connection.get_client_ca_list",
        "src.OpenSSL.crypto.X509.get_subject"
    ],
    "tests.test_ssl.TestMemoryBIO.test_shutdown": [
        "src.OpenSSL.SSL.Connection.bio_shutdown"
    ],
    "tests.test_ssl.TestMemoryBIO.test_socket_connect": [
        "src.OpenSSL.SSL.Connection.send",
        "src.OpenSSL.SSL.Connection.recv"
    ],
    "tests.test_ssl.TestMemoryBIO.test_socket_overrides_memory": [
        "src.OpenSSL.SSL.Connection.bio_shutdown",
        "src.OpenSSL.SSL.Connection.bio_write"
    ],
    "tests.test_ssl.TestMemoryBIO.test_unexpected_EOF": [
        "src.OpenSSL.SSL.Connection.recv",
        "src.OpenSSL.SSL.Connection.sock_shutdown"
    ],
    "tests.test_ssl.TestOCSP.test_callbacks_are_invoked_with_connections": [
        "src.OpenSSL.SSL.Connection.request_ocsp",
        "src.OpenSSL.SSL.Connection.set_connect_state",
        "src.OpenSSL.SSL.Context.set_ocsp_client_callback",
        "src.OpenSSL.SSL.Context.set_ocsp_server_callback"
    ],
    "tests.test_ssl.TestOCSP.test_callbacks_arent_called_by_default": [
        "src.OpenSSL.SSL.Context.set_ocsp_client_callback",
        "src.OpenSSL.SSL.Context.set_ocsp_server_callback"
    ],
    "tests.test_ssl.TestOCSP.test_client_negotiates_without_server": [
        "src.OpenSSL.SSL.Connection.set_connect_state",
        "src.OpenSSL.SSL.Connection.request_ocsp",
        "src.OpenSSL.SSL.Context.set_ocsp_client_callback",
        "src.OpenSSL.SSL.Connection.set_accept_state",
        "src.OpenSSL.SSL.Context.use_certificate"
    ],
    "tests.test_ssl.TestOCSP.test_client_receives_servers_data": [
        "src.OpenSSL.SSL.Context.set_ocsp_server_callback"
    ],
    "tests.test_ssl.TestOCSP.test_client_returns_false_terminates_handshake": [
        "src.OpenSSL.SSL.Context.set_ocsp_server_callback",
        "src.OpenSSL.SSL.Context.set_ocsp_client_callback",
        "src.OpenSSL.SSL.Connection.do_handshake",
        "src.OpenSSL.SSL.Connection.request_ocsp"
    ],
    "tests.test_ssl.TestOCSP.test_exceptions_in_client_bubble_up": [
        "src.OpenSSL.SSL.Context.set_ocsp_client_callback"
    ],
    "tests.test_ssl.TestOCSP.test_exceptions_in_server_bubble_up": [
        "src.OpenSSL.SSL.Context.set_ocsp_server_callback"
    ],
    "tests.test_ssl.TestOCSP.test_opaque_data_is_passed_through": [
        "src.OpenSSL.SSL.Connection.request_ocsp",
        "src.OpenSSL.SSL.Context.set_ocsp_server_callback",
        "src.OpenSSL.SSL.Connection.set_accept_state"
    ],
    "tests.test_ssl.TestOCSP.test_server_must_return_bytes": [
        "src.OpenSSL.SSL.Connection.request_ocsp",
        "src.OpenSSL.SSL.Context.set_ocsp_server_callback",
        "src.OpenSSL.SSL.Context.set_ocsp_client_callback",
        "src.OpenSSL.SSL.Connection.set_accept_state",
        "src.OpenSSL.SSL.Connection.set_connect_state"
    ],
    "tests.test_ssl.TestOCSP.test_server_returns_empty_string": [
        "src.OpenSSL.SSL.Connection.request_ocsp",
        "src.OpenSSL.SSL.Connection.set_accept_state",
        "src.OpenSSL.SSL.Connection.set_connect_state",
        "src.OpenSSL.SSL.Context.set_ocsp_server_callback",
        "src.OpenSSL.SSL.Context.set_ocsp_client_callback"
    ],
    "tests.test_ssl.TestRequires.test_available": [
        "src.OpenSSL.SSL._make_requires",
        "src.OpenSSL.SSL._make_requires.<locals>._requires_decorator"
    ],
    "tests.test_ssl.TestRequires.test_unavailable": [
        "src.OpenSSL.SSL._make_requires.<locals>._requires_decorator.<locals>.explode",
        "src.OpenSSL.SSL._make_requires"
    ],
    "tests.test_ssl.TestServerNameCallback.test_no_servername": [
        "src.OpenSSL.SSL.Context.set_tlsext_servername_callback"
    ],
    "tests.test_ssl.TestServerNameCallback.test_old_callback_forgotten": [
        "src.OpenSSL.SSL.Context.set_tlsext_servername_callback"
    ],
    "tests.test_ssl.TestServerNameCallback.test_servername": [
        "src.OpenSSL.SSL.Connection.set_tlsext_host_name",
        "src.OpenSSL.SSL.Context.set_tlsext_servername_callback"
    ],
    "tests.test_ssl.TestSession.test_construction": [],
    "tests.test_ssl.TestVersion.test_OPENSSL_VERSION_NUMBER": [],
    "tests.test_ssl.TestVersion.test_SSLeay_version": [
        "src.OpenSSL.SSL.OpenSSL_version"
    ],
    "tests.test_util.TestErrors.test_exception_from_error_queue_nonexistent_reason": [
        "src.OpenSSL._util.exception_from_error_queue"
    ],
    "tests.util.EqualityTestsMixin.test_anotherTypeEq": [
        "src.OpenSSL.crypto.get_elliptic_curve"
    ],
    "tests.util.EqualityTestsMixin.test_anotherTypeNe": [
        "src.OpenSSL.crypto._EllipticCurve.__ne__"
    ],
    "tests.util.EqualityTestsMixin.test_delegateNe": [
        "src.OpenSSL.crypto._EllipticCurve.__ne__",
        "src.OpenSSL.crypto.get_elliptic_curve"
    ],
    "tests.util.EqualityTestsMixin.test_delegatedEq": [
        "src.OpenSSL.crypto.get_elliptic_curve"
    ],
    "tests.util.EqualityTestsMixin.test_differentEq": [
        "src.OpenSSL.crypto.get_elliptic_curve"
    ],
    "tests.util.EqualityTestsMixin.test_differentNe": [
        "src.OpenSSL.crypto._EllipticCurve.__ne__"
    ],
    "tests.util.EqualityTestsMixin.test_identicalEq": [
        "src.OpenSSL.crypto.get_elliptic_curve"
    ],
    "tests.util.EqualityTestsMixin.test_identicalNe": [
        "src.OpenSSL.crypto._EllipticCurve.__ne__"
    ],
    "tests.util.EqualityTestsMixin.test_sameEq": [
        "src.OpenSSL.crypto.get_elliptic_curve"
    ],
    "tests.util.EqualityTestsMixin.test_sameNe": [
        "src.OpenSSL.crypto._EllipticCurve.__ne__"
    ]
}